{
  "timestamp": "2026-03-27T01:55:02.271332",
  "ca": {
    "TSX": {
      "value": 32040.01,
      "change": -342.59,
      "changePercent": -1.06
    }
  },
  "crypto": {
    "BTC": {
      "value": 68617.3,
      "change": -2694.36,
      "changePercent": -3.78
    },
    "ETH": {
      "value": 2056.59,
      "change": -111.69,
      "changePercent": -5.15
    },
    "SOL": {
      "value": 86.93,
      "change": -4.77,
      "changePercent": -5.21
    },
    "LINK": {
      "value": 8.9,
      "change": -0.47,
      "changePercent": -5.04
    }
  },
  "stocks": {
    "RY": {
      "price": 222.6,
      "change": -1.91,
      "changePercent": -0.85
    },
    "ENB": {
      "price": 75.7,
      "change": 0.41,
      "changePercent": 0.54
    },
    "SHOP": {
      "price": 161.42,
      "change": -2.3,
      "changePercent": -1.4
    }
  }
}