{
  "timestamp": "2026-03-26T13:45:01.840077",
  "ca": {
    "TSX": {
      "value": 32382.6,
      "change": 441.01,
      "changePercent": 1.38
    }
  },
  "crypto": {
    "BTC": {
      "value": 70500.75,
      "change": -810.91,
      "changePercent": -1.14
    },
    "ETH": {
      "value": 2140.68,
      "change": -27.6,
      "changePercent": -1.27
    },
    "SOL": {
      "value": 90.0,
      "change": -1.7,
      "changePercent": -1.86
    },
    "LINK": {
      "value": 9.18,
      "change": -0.19,
      "changePercent": -2.07
    }
  },
  "stocks": {
    "RY": {
      "price": 224.51,
      "change": 1.33,
      "changePercent": 0.6
    },
    "ENB": {
      "price": 75.29,
      "change": 0.38,
      "changePercent": 0.51
    },
    "SHOP": {
      "price": 163.72,
      "change": 3.88,
      "changePercent": 2.43
    }
  }
}