{
  "timestamp": "2026-03-27T02:00:02.621510",
  "cn": {
    "上证指数": {
      "value": 3889.08,
      "change": 7.8,
      "changePercent": 0.2
    },
    "深证成指": {
      "value": 13606.44,
      "change": 69.84,
      "changePercent": 0.52
    },
    "科创 50": {
      "value": 1288.81,
      "change": -26.6,
      "changePercent": -2.02
    }
  },
  "hk": {
    "恒生指数": {
      "value": 24856.43,
      "change": -479.52,
      "changePercent": -1.89
    },
    "国企指数": {
      "value": 8389.93,
      "change": -192.81,
      "changePercent": -2.25
    },
    "恒生科技": {
      "value": 0,
      "change": 0,
      "changePercent": 0
    }
  },
  "us": {
    "道琼斯": {
      "value": 45965.57,
      "change": -463.92,
      "changePercent": -1.0
    },
    "纳斯达克": {
      "value": 21472.5,
      "change": -457.33,
      "changePercent": -2.09
    },
    "标普 500": {
      "value": 6491.43,
      "change": -100.47,
      "changePercent": -1.52
    }
  },
  "ca": {
    "TSX": {
      "value": 32011.57,
      "change": -371.03,
      "changePercent": -1.15
    },
    "S&P/TSX 60": {
      "value": 0,
      "change": 0,
      "changePercent": 0
    },
    "TSX Venture": {
      "value": 0,
      "change": 0,
      "changePercent": 0
    }
  },
  "crypto": {
    "BTC": {
      "value": 68647.2,
      "change": -2664.47,
      "changePercent": -3.74
    },
    "ETH": {
      "value": 2055.82,
      "change": -112.45,
      "changePercent": -5.19
    },
    "SOL": {
      "value": 86.88,
      "change": -4.82,
      "changePercent": -5.26
    }
  }
}