{
  "timestamp": "2026-03-26T13:55:02.527834",
  "cn": {
    "上证指数": {
      "value": 3894.5,
      "change": 13.22,
      "changePercent": 0.34
    },
    "深证成指": {
      "value": 13642.8,
      "change": 106.2,
      "changePercent": 0.78
    },
    "科创 50": {
      "value": 1290.68,
      "change": -24.74,
      "changePercent": -1.88
    }
  },
  "hk": {
    "恒生指数": {
      "value": 24854.85,
      "change": -481.1,
      "changePercent": -1.9
    },
    "国企指数": {
      "value": 8394.98,
      "change": -187.76,
      "changePercent": -2.19
    },
    "恒生科技": {
      "value": 0,
      "change": 0,
      "changePercent": 0
    }
  },
  "us": {
    "道琼斯": {
      "value": 46429.49,
      "change": 305.43,
      "changePercent": 0.66
    },
    "纳斯达克": {
      "value": 21929.83,
      "change": 167.93,
      "changePercent": 0.77
    },
    "标普 500": {
      "value": 6591.9,
      "change": 35.53,
      "changePercent": 0.54
    }
  },
  "ca": {
    "TSX": {
      "value": 32382.6,
      "change": 441.01,
      "changePercent": 1.38
    },
    "S&P/TSX 60": {
      "value": 0,
      "change": 0,
      "changePercent": 0
    },
    "TSX Venture": {
      "value": 0,
      "change": 0,
      "changePercent": 0
    }
  },
  "crypto": {
    "BTC": {
      "value": 70134.16,
      "change": -1177.5,
      "changePercent": -1.65
    },
    "ETH": {
      "value": 2119.94,
      "change": -48.34,
      "changePercent": -2.23
    },
    "SOL": {
      "value": 89.46,
      "change": -2.24,
      "changePercent": -2.45
    }
  }
}